foc_common/__init__.py
foc_common/logger.py
foc_common-0.0.7.dist-info/LICENSE
foc_common-0.0.7.dist-info/METADATA
foc_common-0.0.7.dist-info/WHEEL
foc_common-0.0.7.dist-info/top_level.txt
foc_common-0.0.7.dist-info/RECORD
