Metadata-Version: 2.1
Name: foc-common
Version: 0.0.7
Summary: A description
License-File: LICENSE
